README
setup.py
xlsimport/__init__.py
xlsimport/models.py
xlsimport/parsers.py
xlsimport.egg-info/PKG-INFO
xlsimport.egg-info/SOURCES.txt
xlsimport.egg-info/dependency_links.txt
xlsimport.egg-info/not-zip-safe
xlsimport.egg-info/requires.txt
xlsimport.egg-info/top_level.txt