Metadata-Version: 1.1
Name: xlsimport
Version: 0.1
Summary: Builton top of xlrd, package provides set of cell parsers that make your import easier.
